useragentxxc/PersonComputer.py
useragentxxc/__init__.py
useragentxxc-1.1.0.dist-info/LICENSE.txt
useragentxxc-1.1.0.dist-info/METADATA
useragentxxc-1.1.0.dist-info/WHEEL
useragentxxc-1.1.0.dist-info/top_level.txt
useragentxxc-1.1.0.dist-info/RECORD
