Metadata-Version: 2.1
Name: useragentxxc
Version: 1.1.0
Summary: Random generation of User agent for PC and mobile
Home-page: https://github.com/clearDreamXXC/user-agent
Author: clearDreamXXC
Author-email: 1586616064@qq.com
License: MIT
Platform: UNKNOWN
